codac_for_matlab/__init__.py
codac_for_matlab/core.cp310-win32.pyd
codac_for_matlab/graphics.cp310-win32.pyd
codac_for_matlab/unsupported.cp310-win32.pyd
codac_for_matlab/version.py
codac_for_matlab/tests/__init__.py
codac_for_matlab/tests/codac2_tests.py
codac_for_matlab-2.0.0.dev1.dist-info/METADATA
codac_for_matlab-2.0.0.dev1.dist-info/WHEEL
codac_for_matlab-2.0.0.dev1.dist-info/top_level.txt
codac_for_matlab-2.0.0.dev1.dist-info/RECORD
