Metadata-Version: 2.1
Name: codac-for-matlab
Version: 2.0.0.dev1
Summary: Codac is a library providing tools for constraint programming over reals and trajectories.
Home-page: http://codac.io
Author: Simon Rohou, Benoit Desrochers, Fabrice Le Bars
Author-email: simon.rohou@ensta-bretagne.fr
License: LGPLv3+
Classifier: Development Status :: 3 - Alpha
Classifier: Topic :: Scientific/Engineering :: Mathematics
Classifier: License :: OSI Approved :: GNU Lesser General Public License v3 or later (LGPLv3+)
Requires-Dist: pip >=19.0.0
Requires-Dist: vibes
